setup.py
swg/__init__.py
swg/engine.py
swg/swg
swg/swg-wordpress
swg.egg-info/PKG-INFO
swg.egg-info/SOURCES.txt
swg.egg-info/dependency_links.txt
swg.egg-info/not-zip-safe
swg.egg-info/requires.txt
swg.egg-info/top_level.txt
swg/basic/robots.txt
swg/basic/swg.cfg
swg/basic/css/style.css
swg/basic/db/Your Name Here.txt
swg/basic/db/categories.txt
swg/basic/db/pages/0.txt
swg/basic/db/pages/1.txt
swg/basic/db/pages/2.txt
swg/basic/images/arrow.png
swg/basic/images/arrow.png.1
swg/basic/images/arrow.png.2
swg/basic/images/author.png
swg/basic/images/author.png.1
swg/basic/images/author.png.2
swg/basic/images/bg-meta.gif
swg/basic/images/bg.jpg
swg/basic/images/bg.jpg.1
swg/basic/images/bg.png
swg/basic/images/bg.png.1
swg/basic/images/boat.jpg
swg/basic/images/category.png
swg/basic/images/category.png.1
swg/basic/images/comments.png
swg/basic/images/comments.png.1
swg/basic/images/contentbg.png
swg/basic/images/contentbg.png.1
swg/basic/images/date.png
swg/basic/images/date.png.1
swg/basic/images/edit.png
swg/basic/images/edit.png.1
swg/basic/images/header-bg-sm.jpg
swg/basic/images/menubar.png
swg/basic/images/search-bg.png
swg/basic/images/search-go.png
swg/basic/images/tags.png
swg/basic/images/your-name-here.png
swg/basic/templates/author.tpl
swg/basic/templates/category.tpl
swg/basic/templates/feed.tpl
swg/basic/templates/footer.tpl
swg/basic/templates/header.tpl
swg/basic/templates/index.tpl
swg/basic/templates/page.tpl
swg/basic/templates/sidebar.tpl
swg/basic/templates/sitemap.tpl
swg/basic/templates/tag.tpl
swg/core/__init__.py
swg/core/authormanager.py
swg/core/authorparser.py
swg/core/categorymanager.py
swg/core/config.py
swg/core/itemparser.py
swg/core/pageparser.py
swg/core/pager.py
swg/core/tagmanager.py
swg/core/templatemanager.py
swg/entities/__init__.py
swg/entities/author.py
swg/entities/category.py
swg/entities/item.py
swg/entities/page.py
swg/entities/tag.py